tstr/__init__.py
tstr/_compat.py
tstr/_interpolation_tools.py
tstr/_template.py
tstr/_template.pyi
tstr/_template_tools.py
tstr/py.typed
tstr/ext/__init__.py
tstr/ext/_html.py
tstr/ext/_logging.py
tstr/ext/_sqlite.py
tstr/ext/py.typed
tstr-0.4.0.post1.dist-info/METADATA
tstr-0.4.0.post1.dist-info/WHEEL
tstr-0.4.0.post1.dist-info/licenses/LICENSE
tstr-0.4.0.post1.dist-info/RECORD
