Metadata-Version: 2.4
Name: tstr
Version: 0.4.0.post1
Summary: Template string utilities and backports
Project-URL: Repository, https://github.com/ilotoki0804/tstr
Author-email: ilotoki0804 <ilotoki0804@gmail.com>
License-Expression: Apache-2.0
License-File: LICENSE
Keywords: backport,pep 750,pep-750,pep750,string,t-string,template,template string,tstring,utility
Classifier: Intended Audience :: Developers
Classifier: License :: OSI Approved :: Apache Software License
Classifier: Operating System :: OS Independent
Classifier: Programming Language :: Python :: 3
Classifier: Programming Language :: Python :: 3.10
Classifier: Programming Language :: Python :: 3.11
Classifier: Programming Language :: Python :: 3.12
Classifier: Programming Language :: Python :: 3.13
Classifier: Programming Language :: Python :: 3.14
Classifier: Topic :: Software Development
Classifier: Topic :: Text Processing
Classifier: Typing :: Typed
Requires-Python: >=3.10
